odoorpc-stubs/__init__.pyi
odoorpc-stubs/db.pyi
odoorpc-stubs/env.pyi
odoorpc-stubs/error.pyi
odoorpc-stubs/fields.pyi
odoorpc-stubs/models.pyi
odoorpc-stubs/odoo.pyi
odoorpc-stubs/py.typed
odoorpc-stubs/report.pyi
odoorpc-stubs/rpc/__init__.pyi
odoorpc-stubs/rpc/error.pyi
odoorpc-stubs/rpc/jsonrpclib.pyi
odoorpc-stubs/session.pyi
odoorpc-stubs/tools.pyi
odoorpc_stubs-0.1.0.dev2.dist-info/METADATA
odoorpc_stubs-0.1.0.dev2.dist-info/WHEEL
odoorpc_stubs-0.1.0.dev2.dist-info/RECORD
